README.md
setup.cfg
setup.py
cv2studio/__init__.py
cv2studio/gui.py
cv2studio.egg-info/PKG-INFO
cv2studio.egg-info/SOURCES.txt
cv2studio.egg-info/dependency_links.txt
cv2studio.egg-info/requires.txt
cv2studio.egg-info/top_level.txt
cv2studio/components/__init__.py