Metadata-Version: 2.1
Name: cv2studio
Version: 1.0.1
Summary: Chain-based framework to split image processing into components.
Home-page: https://github.com/VoIlAlex/cv2studio
Author: Ilya Vouk
Author-email: ilya.vouk@gmail.com
License: MIT
Download-URL: https://github.com/VoIlAlex/cv2studio/archive/1.0.1.tar.gz
Keywords: OpenCV,Computer Vision,Framework,Wrapper,Components
Platform: UNKNOWN
Classifier: Development Status :: 3 - Alpha
Classifier: Intended Audience :: Developers
Classifier: Topic :: Software Development :: Libraries :: Application Frameworks
Classifier: License :: OSI Approved :: MIT License
Classifier: Programming Language :: Python :: 3.6
Classifier: Programming Language :: Python :: 3.7
Classifier: Programming Language :: Python :: 3.8
